Metadata-Version: 2.1
Name: xmlmicroparser
Version: 1.0
Summary: A tiny xml parser without DTD/XSLT/SAX functionality.
Author: Claus Prüfer
Author-email: Claus Prüfer <pruefer@webcodex.de>
Project-URL: Homepage, https://github.com/clauspruefer/python-xml-microparser
Project-URL: Issues, https://github.com/clauspruefer/python-xml-microparser/issues
Project-URL: Documentation, https://pythondocs.webcodex.de/xml-microparser
Classifier: Programming Language :: Python :: 3
Classifier: License :: OSI Approved :: GNU General Public License v3 (GPLv3)
Classifier: Operating System :: Microsoft :: Windows
Classifier: Operating System :: POSIX :: Linux
Requires-Python: >=3.8
License-File: LICENSE
